apim_subscriptions_manager/__init__.py
apim_subscriptions_manager/apim_subscriptions_manager.py
apim_subscription_manager-0.0.3.dist-info/METADATA
apim_subscription_manager-0.0.3.dist-info/WHEEL
apim_subscription_manager-0.0.3.dist-info/top_level.txt
apim_subscription_manager-0.0.3.dist-info/RECORD
