Metadata-Version: 2.1
Name: apim-subscription-manager
Version: 0.0.3
Summary: Utility that interacts with Azure API Management subscription
Author: Ivica Matic
Author-email: <ivica.matic@spatialdays.com>
Keywords: apim,azure
Classifier: Development Status :: 1 - Planning
Classifier: Intended Audience :: Developers
Classifier: Programming Language :: Python :: 3
Classifier: Operating System :: Unix
Requires-Dist: requests ==2.31.0
